full_adder.vhdl
library ieee;
use ieee.std_logic_1164.all;


entity full_adder is
	
	port(	a: in std_logic;
		b: in std_logic;
		cin: in std_logic;
		sum: out std_logic;
		cout: out std_logic
	);

end entity full_adder;

architecture behav of full_adder is

	signal t0, t1, t2: std_logic;

begin

	t0 <= a xor b;
	t1 <= t0 and cin;
	t2 <= a and b;
	sum <= t0 xor cin;
	cout <= t1 or t2;

end behav;

addsub4bit.vhdl
library ieee;
use ieee.std_logic_1164.all;

entity addsub4bit is

	port(	a: in std_logic_vector(3 downto 0);
		b: in std_logic_vector(3 downto 0);
		sub: in std_logic;
		s: out std_logic_vector(3 downto 0);
		over: out std_logic;
		under: out std_logic
	);

end entity addsub4bit;

architecture behav of addsub4bit is

	component full_adder

		port(	a: in std_logic;
			b: in std_logic;
			cin: in std_logic;
			sum: out std_logic;
			cout: out std_logic
		);

	end component;

	signal newb0, newb1, newb2, newb3, c1, c2, c3, c4, sig_bit: std_logic;

	begin

	newb0 <= b(0) xor sub;
	newb1 <= b(1) xor sub;
	newb2 <= b(2) xor sub;
	newb3 <= b(3) xor sub;

	fa0: full_adder port map(	a => a(0),
					b => newb0,
					cin => sub,
					sum => s(0),
					cout => c1);

	fa1: full_adder port map(	a => a(1),
					b => newb1,
					cin => c1,
					sum => s(1),
					cout => c2);

	fa2: full_adder port map(	a => a(2),
					b => newb2,
					cin => c2,
					sum => s(2),
					cout => c3);

	fa3: full_adder port map(	a => a(3),
					b => newb3,
					cin => c3,
					sum => sig_bit,
					cout => c4);

	under <= (not sig_bit and c4 and a(3) and newb3);
	over <= (not a(3) and not b(3)) and sig_bit;
	s(3) <= sig_bit; 

end behav;

addsub4bit_tb.vhdl
library ieee;
use ieee.std_logic_1164.all;

-- A testbench has no ports
entity addsub4bit_tb is
end addsub4bit_tb;

architecture behavioral of addsub4bit_tb is
-- Declaration of the component to be instantiated
  component addsub4bit
    port(a     : in  std_logic_vector(3 downto 0);
         b     : in  std_logic_vector(3 downto 0);
         sub   : in  std_logic;
         s     : out std_logic_vector(3 downto 0);
         over  : out std_logic;
         under : out std_logic
         );
  end component;
-- Specifies which entity is bound with the component
  signal tb_a, tb_b, tb_s          : std_logic_vector(3 downto 0);
  signal tb_sub, tb_over, tb_under : std_logic;
begin
-- Component instantiation
  adder0 : addsub4bit port map(a     => tb_a,
                                b     => tb_b,
                                s     => tb_s,
                                sub   => tb_sub,
                                over  => tb_over,
                                under => tb_under);
-- This process does the real job
  process
    type pattern_type is record
-- The inputs of the adder
      tb_a, tb_b        : std_logic_vector(3 downto 0);
      tb_sub          : std_logic;
-- Expected outputs of adder
      tb_s            : std_logic_vector(3 downto 0);
      tb_over, tb_under : std_logic;
    end record;
-- The patterns to apply
    type pattern_array is array (natural range <>) of pattern_type;
    constant patterns : pattern_array :=
      (("0001", "0001", '0', "0010", '0', '0'), -- 1 + 1 = 2
       ("0001", "1111", '0', "0000", '0', '0'), -- 1 +-1 = 0
       ("1111", "1111", '0', "1110", '0', '0'), -- -1+-1 =-2
       ("0001", "0001", '1', "0000", '0', '0'), -- 1 - 1 = 0
       ("1111", "0001", '1', "1110", '0', '0'), -- -1- 1 =-2
       ("1111", "1111", '1', "0000", '0', '0'), -- -1--1 = 0
       ("0111", "0001", '0', "1000", '1', '0'), -- 7 + 1 =-8
       ("1001", "0010", '1', "0111", '0', '1'));-- -7- 2 = 7
  begin
-- Check each pattern    
    for n in patterns'range loop
-- Set the inputs      
      tb_a <= patterns(n).tb_a;
      tb_b <= patterns(n).tb_b;
      tb_sub <= patterns(n).tb_sub;
-- Wait for the result      
      wait for 1 ns;
-- Check the output      
      assert tb_s = patterns(n).tb_s
        report "bad output value s" severity error;
      assert tb_over = patterns(n).tb_over
        report "bad output value o" severity error;
      assert tb_under = patterns(n).tb_under
        report "bad output value u" severity error;
    end loop;
    assert false report "end of test" severity note;
-- Wait forever; this will finish the simulation
    wait;
  end process;
end behavioral;

addsub4bit.vcd
$date
  Tue Apr  1 22:00:37 2025
$end
$version
  GHDL v0
$end
$timescale
  1 fs
$end
$scope module standard $end
$upscope $end
$scope module std_logic_1164 $end
$upscope $end
$scope module addsub4bit_tb $end
$var reg 4 ! tb_a[3:0] $end
$var reg 4 " tb_b[3:0] $end
$var reg 4 # tb_s[3:0] $end
$var reg 1 $ tb_sub $end
$var reg 1 % tb_over $end
$var reg 1 & tb_under $end
$scope module adder0 $end
$var reg 4 ' a[3:0] $end
$var reg 4 ( b[3:0] $end
$var reg 1 ) sub $end
$var reg 4 * s[3:0] $end
$var reg 1 + over $end
$var reg 1 , under $end
$var reg 1 - newb0 $end
$var reg 1 . newb1 $end
$var reg 1 / newb2 $end
$var reg 1 0 newb3 $end
$var reg 1 1 c1 $end
$var reg 1 2 c2 $end
$var reg 1 3 c3 $end
$var reg 1 4 c4 $end
$var reg 1 5 sig_bit $end
$scope module fa0 $end
$var reg 1 6 a $end
$var reg 1 7 b $end
$var reg 1 8 cin $end
$var reg 1 9 sum $end
$var reg 1 : cout $end
$var reg 1 ; t0 $end
$var reg 1 < t1 $end
$var reg 1 = t2 $end
$upscope $end
$scope module fa1 $end
$var reg 1 > a $end
$var reg 1 ? b $end
$var reg 1 @ cin $end
$var reg 1 A sum $end
$var reg 1 B cout $end
$var reg 1 C t0 $end
$var reg 1 D t1 $end
$var reg 1 E t2 $end
$upscope $end
$scope module fa2 $end
$var reg 1 F a $end
$var reg 1 G b $end
$var reg 1 H cin $end
$var reg 1 I sum $end
$var reg 1 J cout $end
$var reg 1 K t0 $end
$var reg 1 L t1 $end
$var reg 1 M t2 $end
$upscope $end
$scope module fa3 $end
$var reg 1 N a $end
$var reg 1 O b $end
$var reg 1 P cin $end
$var reg 1 Q sum $end
$var reg 1 R cout $end
$var reg 1 S t0 $end
$var reg 1 T t1 $end
$var reg 1 U t2 $end
$upscope $end
$upscope $end
$upscope $end
$enddefinitions $end
#0
b0001 !
b0001 "
b0010 #
0$
0%
0&
b0001 '
b0001 (
0)
b0010 *
0+
0,
1-
0.
0/
00
11
02
03
04
05
16
17
08
09
1:
0;
0<
1=
0>
0?
1@
1A
0B
0C
0D
0E
0F
0G
0H
0I
0J
0K
0L
0M
0N
0O
0P
0Q
0R
0S
0T
0U
#1000000
b1111 "
b0000 #
b1111 (
b0000 *
1.
1/
10
12
13
14
05
1?
0A
1B
1C
1D
1G
1H
0I
1J
1K
1L
1O
1P
0Q
1R
1S
1T
#2000000
b1111 !
b1110 #
0&
b1111 '
b1110 *
0,
15
1>
1A
0C
0D
1E
1F
1I
0K
0L
1M
1N
1Q
0S
0T
1U
#3000000
b0001 !
b0001 "
b0000 #
1$
0%
b0001 '
b0001 (
1)
b0000 *
0+
0-
11
12
13
14
05
07
18
09
1:
1;
1<
0=
0>
1@
0A
1B
1C
1D
0E
0F
1H
0I
1J
1K
1L
0M
0N
1P
0Q
1R
1S
1T
0U
#4000000
b1111 !
b1110 #
0&
b1111 '
b1110 *
0,
15
1>
1A
0C
0D
1E
1F
1I
0K
0L
1M
1N
1Q
0S
0T
1U
#5000000
b1111 "
b0000 #
b1111 (
b0000 *
0.
0/
00
12
13
14
05
0?
0A
1B
1C
1D
0E
0G
1H
0I
1J
1K
1L
0M
0O
1P
0Q
1R
1S
1T
0U
#6000000
b0111 !
b0001 "
b1000 #
0$
1%
b0111 '
b0001 (
0)
b1000 *
1+
1-
11
12
13
04
15
17
08
09
1:
0;
0<
1=
1@
0A
1B
1D
1H
0I
1J
1L
0N
1P
1Q
0R
0S
0T
#7000000
b1001 !
b0010 "
b0111 #
1$
0%
1&
b1001 '
b0010 (
1)
b0111 *
0+
1,
1/
10
02
03
14
05
18
19
0>
1A
0B
0C
0D
0F
1G
0H
1I
0J
1K
0L
1N
1O
0P
0Q
1R
0S
0T
1U
